netint_agents_sdk/__init__.py
netint_agents_sdk/client.py
netint_agents_sdk/config.py
netint_agents_sdk/exceptions.py
netint_agents_sdk/models/__init__.py
netint_agents_sdk/models/environment.py
netint_agents_sdk/models/git.py
netint_agents_sdk/models/instance.py
netint_agents_sdk/models/task.py
netint_agents_sdk/resources/__init__.py
netint_agents_sdk/resources/base.py
netint_agents_sdk/resources/environments.py
netint_agents_sdk/resources/git.py
netint_agents_sdk/resources/instances.py
netint_agents_sdk/resources/tasks.py
netint_agents_sdk/utils/__init__.py
netint_agents_sdk/utils/http.py
netint_agents_sdk-0.3.1.dist-info/licenses/LICENSE
netint_agents_sdk-0.3.1.dist-info/METADATA
netint_agents_sdk-0.3.1.dist-info/WHEEL
netint_agents_sdk-0.3.1.dist-info/top_level.txt
netint_agents_sdk-0.3.1.dist-info/RECORD
